MANIFEST.in
README.txt
setup.py
docs/HISTORY.txt
docs/LICENSE.GPL
docs/LICENSE.txt
src/zopemetadatamaker/__init__.py
src/zopemetadatamaker/zopemetadatamaker
zopemetadatamaker.egg-info/PKG-INFO
zopemetadatamaker.egg-info/SOURCES.txt
zopemetadatamaker.egg-info/dependency_links.txt
zopemetadatamaker.egg-info/entry_points.txt
zopemetadatamaker.egg-info/not-zip-safe
zopemetadatamaker.egg-info/requires.txt
zopemetadatamaker.egg-info/top_level.txt