Metadata-Version: 1.0
Name: zopemetadatamaker
Version: 0.1.0
Summary: Bulk creation of .metadata files for Zope skins resources
Home-page: http://svn.plone.org/svn/collective/zopemetadatamaker
Author: keul
Author-email: luca@keul.it
License: GPL
Keywords: file zope metadata creator skins
Platform: UNKNOWN
Classifier: Development Status :: 4 - Beta
Classifier: Intended Audience :: Developers
Classifier: License :: OSI Approved :: GNU General Public License (GPL)
Classifier: Operating System :: OS Independent
Classifier: Programming Language :: Python
Classifier: Framework :: Zope2
Classifier: Framework :: Plone
Classifier: Topic :: Utilities
